{
  "name": "TCCUOTAPROPUESTA",
  "fields": [
    {
      "fieldName": "idCuotaPropuesta",
      "fieldType": "Long",
      "options": {
        "id": true
      }
    },
    {
      "fieldName": "edad",
      "fieldType": "String",
      "fieldValidateRules": ["required"]
    },
    {
      "fieldName": "valorVg",
      "fieldType": "Long",
      "fieldValidateRules": ["required"]
    },
    {
      "fieldName": "valorBipTres",
      "fieldType": "Long",
      "fieldValidateRules": ["required"]
    },
    {
      "fieldName": "valorBit",
      "fieldType": "Long",
      "fieldValidateRules": ["required"]
    },
    {
      "fieldName": "valorDi",
      "fieldType": "Long",
      "fieldValidateRules": ["required"]
    }
  ],
  "relationships": [],
  "entityTableName": "tccuotapropuesta",
  "dto": "no",
  "pagination": "no",
  "service": "no",
  "jpaMetamodelFiltering": false,
  "fluentMethods": true,
  "readOnly": false,
  "embedded": false,
  "applications": "*",
  "changelogDate": "20211001044456"
}
